fds/__init__.py
fds/sdk/__init__.py
fds/sdk/FactSetTermsandConditions/__init__.py
fds/sdk/FactSetTermsandConditions/api_client.py
fds/sdk/FactSetTermsandConditions/configuration.py
fds/sdk/FactSetTermsandConditions/exceptions.py
fds/sdk/FactSetTermsandConditions/model_utils.py
fds/sdk/FactSetTermsandConditions/rest.py
fds/sdk/FactSetTermsandConditions/api/__init__.py
fds/sdk/FactSetTermsandConditions/api/agents_api.py
fds/sdk/FactSetTermsandConditions/api/convertibles_api.py
fds/sdk/FactSetTermsandConditions/api/coupons_api.py
fds/sdk/FactSetTermsandConditions/api/covenants_api.py
fds/sdk/FactSetTermsandConditions/api/issue_size_api.py
fds/sdk/FactSetTermsandConditions/api/redemptions_api.py
fds/sdk/FactSetTermsandConditions/api/terms__conditions_api.py
fds/sdk/FactSetTermsandConditions/api/underwriters_api.py
fds/sdk/FactSetTermsandConditions/api/use_of_proceeds_api.py
fds/sdk/FactSetTermsandConditions/apis/__init__.py
fds/sdk/FactSetTermsandConditions/model/__init__.py
fds/sdk/FactSetTermsandConditions/model/agent.py
fds/sdk/FactSetTermsandConditions/model/agents_response.py
fds/sdk/FactSetTermsandConditions/model/convertible_details.py
fds/sdk/FactSetTermsandConditions/model/convertible_details_response.py
fds/sdk/FactSetTermsandConditions/model/convertible_history.py
fds/sdk/FactSetTermsandConditions/model/convertible_history_response.py
fds/sdk/FactSetTermsandConditions/model/convertible_triggers.py
fds/sdk/FactSetTermsandConditions/model/convertible_triggers_response.py
fds/sdk/FactSetTermsandConditions/model/coupon_history.py
fds/sdk/FactSetTermsandConditions/model/coupon_history_response.py
fds/sdk/FactSetTermsandConditions/model/coupon_schedules.py
fds/sdk/FactSetTermsandConditions/model/coupon_schedules_response.py
fds/sdk/FactSetTermsandConditions/model/covenant_detail.py
fds/sdk/FactSetTermsandConditions/model/covenant_details_response.py
fds/sdk/FactSetTermsandConditions/model/error_response.py
fds.sdk.FactSetTermsandConditions-1.0.13.dist-info/LICENSE
fds.sdk.FactSetTermsandConditions-1.0.13.dist-info/METADATA
fds.sdk.FactSetTermsandConditions-1.0.13.dist-info/WHEEL
fds.sdk.FactSetTermsandConditions-1.0.13.dist-info/top_level.txt
fds.sdk.FactSetTermsandConditions-1.0.13.dist-info/RECORD
